{
  "uuid": "a87c4d51e0e6469886407e3c51f9bd78",
  "file_path": "https://cdn.sh-genius.cn/a6cf60bf9ea74ed7e8cb3d3e51025080.dcz",
  "file_md5": "a6cf60bf9ea74ed7e8cb3d3e51025080",
  "title": "普通高中 英语 选择性必修第三册 教学参考资料",
  "cover_path": "https://cdn.sh-genius.cn/cover/a87c4d51e0e6469886407e3c51f9bd78/a87c4d51e0e6469886407e3c51f9bd78.jpg?x-oss-process=image/resize,m_lfit,h_500&t=/a87c4d51e0e6469886407e3c51f9bd78.jpg",
  "is_current_term": 0,
  "use_year": "2024",
  "text_start_page": 12,
  "short_title": "普通高中教科书·英语（选择性必修第三册）教学参考资料",
  "update_time": "2025-02-17 16:16:34",
  "subject": "YY",
  "used_grade_semesters": [
    {
      "grade_level": "ELEVENTH_GRADE",
      "used_semester_phases": [
        {
          "semester_phase": "SECOND_SEMESTER",
          "semester_phase_str": "下学期",
          "semester_phase_code": "02"
        }
      ],
      "grade_level_code": "11",
      "grade_level_str": "高二"
    }
  ],
  "textbook_material_type": "BASIC",
  "publisher": "SHWJ",
  "grade": "ELEVENTH_GRADE",
  "term": "SECOND_SEMESTER",
  "use_type": "JSYS",
  "isbn": "9787544670289",
  "status": "1",
  "subject_str": "英语"
}